MANIFEST.in
README.txt
setup.cfg
setup.py
collective/__init__.py
collective.imstransport.egg-info/PKG-INFO
collective.imstransport.egg-info/SOURCES.txt
collective.imstransport.egg-info/dependency_links.txt
collective.imstransport.egg-info/entry_points.txt
collective.imstransport.egg-info/namespace_packages.txt
collective.imstransport.egg-info/not-zip-safe
collective.imstransport.egg-info/requires.txt
collective.imstransport.egg-info/top_level.txt
collective/imstransport/IMS_exceptions.py
collective/imstransport/__init__.py
collective/imstransport/config.py
collective/imstransport/configure.zcml
collective/imstransport/version.txt
collective/imstransport/browser/__init__.py
collective/imstransport/browser/configure.zcml
collective/imstransport/browser/exportform.py
collective/imstransport/browser/importform.py
collective/imstransport/browser/imschoice.pt
collective/imstransport/locales/IMSTransport.pot
collective/imstransport/locales/af/LC_MESSAGES/IMSTransport.mo
collective/imstransport/locales/af/LC_MESSAGES/IMSTransport.po
collective/imstransport/locales/ar/LC_MESSAGES/IMSTransport.mo
collective/imstransport/locales/ar/LC_MESSAGES/IMSTransport.po
collective/imstransport/locales/bn/LC_MESSAGES/IMSTransport.mo
collective/imstransport/locales/bn/LC_MESSAGES/IMSTransport.po
collective/imstransport/locales/ca/LC_MESSAGES/IMSTransport.mo
collective/imstransport/locales/ca/LC_MESSAGES/IMSTransport.po
collective/imstransport/locales/de/LC_MESSAGES/IMSTransport.mo
collective/imstransport/locales/de/LC_MESSAGES/IMSTransport.po
collective/imstransport/locales/en/LC_MESSAGES/IMSTransport.mo
collective/imstransport/locales/en/LC_MESSAGES/IMSTransport.po
collective/imstransport/locales/es/LC_MESSAGES/IMSTransport.mo
collective/imstransport/locales/es/LC_MESSAGES/IMSTransport.po
collective/imstransport/locales/fr/LC_MESSAGES/IMSTransport.mo
collective/imstransport/locales/fr/LC_MESSAGES/IMSTransport.po
collective/imstransport/locales/hi/LC_MESSAGES/IMSTransport.mo
collective/imstransport/locales/hi/LC_MESSAGES/IMSTransport.po
collective/imstransport/locales/hu/LC_MESSAGES/IMSTransport.mo
collective/imstransport/locales/hu/LC_MESSAGES/IMSTransport.po
collective/imstransport/locales/it/LC_MESSAGES/IMSTransport.mo
collective/imstransport/locales/it/LC_MESSAGES/IMSTransport.po
collective/imstransport/locales/ja/LC_MESSAGES/IMSTransport.mo
